neuroplotlib/__init__.py
neuroplotlib/core.py
neuroplotlib/utils.py
neuroplotlib/version.py
neuroplotlib/test/__init__.py
neuroplotlib/test/test_core.py
neuroplotlib-0.2.1.dist-info/METADATA
neuroplotlib-0.2.1.dist-info/WHEEL
neuroplotlib-0.2.1.dist-info/top_level.txt
neuroplotlib-0.2.1.dist-info/RECORD
