Metadata-Version: 2.1
Name: neuroplotlib
Version: 0.2.1
Summary: Python package for visualization of neurons in LFPy.
Home-page: https://github.com/alejoe91/neuroplotlib
Author: Alessio Buccino
Author-email: alessiop.buccino@gmail.com
License: UNKNOWN
Platform: UNKNOWN
Classifier: Programming Language :: Python :: 3
Classifier: License :: OSI Approved :: GNU General Public License v3 (GPLv3)
Classifier: Operating System :: OS Independent
Requires-Dist: numpy
Requires-Dist: matplotlib
